lineprofilergui/__init__.py
lineprofilergui/__main__.py
lineprofilergui/config.py
lineprofilergui/gui.py
lineprofilergui/main.py
lineprofilergui/process.py
lineprofilergui/settings.py
lineprofilergui/tree.py
lineprofilergui/utils.py
line_profiler_gui-0.2.dist-info/LICENSE.txt
line_profiler_gui-0.2.dist-info/METADATA
line_profiler_gui-0.2.dist-info/WHEEL
line_profiler_gui-0.2.dist-info/entry_points.txt
line_profiler_gui-0.2.dist-info/top_level.txt
line_profiler_gui-0.2.dist-info/RECORD
