Metadata-Version: 2.1
Name: line-profiler-gui
Version: 0.2
Summary: A Qt GUI to run and display line by line profiling data using line_profiler
Home-page: https://pypi.org/project/line-profiler-gui/
Author: Joseph Martinot-Lagarde
Author-email: contrebasse+pypi@gmail.com
License: MIT
Project-URL: Bug Tracker, https://github.com/Nodd/lineprofilergui/issues
Project-URL: Github, https://github.com/Nodd/lineprofilergui
Keywords: profiling,profiler,line_profiler,gui,Qt
Platform: UNKNOWN
Classifier: Development Status :: 3 - Alpha
Classifier: Environment :: MacOS X
Classifier: Environment :: Win32 (MS Windows)
Classifier: Environment :: X11 Applications :: Qt
Classifier: Intended Audience :: Developers
Classifier: License :: OSI Approved :: MIT License
Classifier: Operating System :: OS Independent
Classifier: Programming Language :: Python :: 3
Classifier: Programming Language :: Python :: 3 :: Only
Classifier: Programming Language :: Python :: 3.8
Classifier: Programming Language :: Python :: 3.9
Classifier: Programming Language :: Python :: 3.10
Classifier: Topic :: Software Development
Classifier: Topic :: System :: Benchmark
Classifier: Topic :: Utilities
Requires-Python: >=3.8
License-File: LICENSE.txt
Requires-Dist: line-profiler
Requires-Dist: qtpy
Provides-Extra: pyqt5
Requires-Dist: pyqt5 ; extra == 'pyqt5'
Provides-Extra: pyside2
Requires-Dist: pyside2 ; extra == 'pyside2'
Provides-Extra: test
Requires-Dist: pytest ; extra == 'test'
Requires-Dist: pytest-qt ; extra == 'test'
Requires-Dist: pytest-cov ; extra == 'test'
